httpstat.py
httpstat-1.3.2.dist-info/LICENSE
httpstat-1.3.2.dist-info/METADATA
httpstat-1.3.2.dist-info/WHEEL
httpstat-1.3.2.dist-info/entry_points.txt
httpstat-1.3.2.dist-info/top_level.txt
httpstat-1.3.2.dist-info/RECORD
