Metadata-Version: 2.1
Name: httpstat
Version: 1.3.2
Summary: curl statistics made simple
Home-page: https://github.com/reorx/httpstat
Author: reorx
Author-email: novoreorx@gmail.com
License: License :: OSI Approved :: MIT License
License-File: LICENSE
